[
  {
    "lat": 36.70161741216705,
    "lng": -4.462113578808766,
    "title": "ASOC. DE FERIANTES DE MÁLAGA/1-2"
  },
  {
    "lat": 36.70180909541306,
    "lng": -4.4621902644467192,
    "title": "EL REVUELO/3"
  },
  {
    "lat": 36.70188323691776,
    "lng": -4.462230862725636,
    "title": "PEÑA CABALLISTA MONTECLARO/4"
  },
  { "lat": 36.7019718449637, "lng": -4.4622692055446125, "title": "LULU/5" },
  {
    "lat": 36.70206587788032,
    "lng": -4.462325592043109,
    "title": "EL RUEDO/6"
  },
  {
    "lat": 36.70216533564772,
    "lng": -4.462397766761183,
    "title": "PEÑA RINCÓN DE CALLE ANCHA/7-8"
  },
  {
    "lat": 36.70230095966858,
    "lng": -4.462458664179557,
    "title": "PEÑA MARTIRICOS/9"
  },
  {
    "lat": 36.70238052564944,
    "lng": -4.462508284298233,
    "title": "TREINTA AMIGOS/10"
  },
  {
    "lat": 36.70272235346019,
    "lng": -4.462695564756779,
    "title": "PEÑA RECREATIVA PALESTINA/11-12"
  },
  {
    "lat": 36.702845105431855,
    "lng": -4.462789660970449,
    "title": "PEÑA PORTADA ALTA/13-14"
  },
  {
    "lat": 36.70300749575984,
    "lng": -4.462886946886278,
    "title": "CALLE LARIOS/15"
  },
  {
    "lat": 36.7030867728032,
    "lng": -4.462904490248149,
    "title": "AMIGOS DE BENJAMÍN/16"
  },
  {
    "lat": 36.70330182399129,
    "lng": -4.463058795863189,
    "title": "EL MALAGUITA/17-18"
  },
  {
    "lat": 36.70361432783226,
    "lng": -4.463175607167066,
    "title": "LA TAJÁ/19-20"
  },
  {
    "lat": 36.70373836156233,
    "lng": -4.463337745595518,
    "title": "LA RESERVA 12/21-22"
  },
  {
    "lat": 36.70391684664892,
    "lng": -4.463427599600725,
    "title": "PEÑA ER SALERO/23-24"
  },
  {
    "lat": 36.70425806745534,
    "lng": -4.4636148577665935,
    "title": "LA CANASTA/25-26"
  },
  {
    "lat": 36.70446546983294,
    "lng": -4.463777618243648,
    "title": "FEDERACIÓN MALAGUEÑA DE PEÑAS/27-28"
  },
  {
    "lat": 36.70466927771992,
    "lng": -4.463863774004584,
    "title": "EL PIMPI/29-30"
  },
  {
    "lat": 36.70480813580906,
    "lng": -4.4639298617954095,
    "title": "SAN MIGUEL/31"
  },
  {
    "lat": 36.70505522679777,
    "lng": -4.463984070531394,
    "title": "PTV MÁLAGA/32-33-34"
  },
  {
    "lat": 36.705353324189595,
    "lng": -4.464236604337986,
    "title": "LOS MIMBRALES/35-36"
  },
  {
    "lat": 36.705537765148755,
    "lng": -4.464353888259344,
    "title": "LE GRAND PERCHELERA/37-38"
  },
  {
    "lat": 36.70184310807277,
    "lng": -4.4615306013174125,
    "title": "EL PALMERAL ADN/43"
  },
  {
    "lat": 36.701954113088796,
    "lng": -4.461596982606188,
    "title": "CENTRAL CIUDADANA LA MARQUESA/44"
  },
  {
    "lat": 36.70205935634472,
    "lng": -4.461672479576877,
    "title": "CC.OO MÁLAGA/45-46"
  },
  {
    "lat": 36.702220373057365,
    "lng": -4.4617411862066785,
    "title": "LA MASCARADA/47-48"
  },
  {
    "lat": 36.70237520657572,
    "lng": -4.461844451257438,
    "title": "PEÑA ATLÉTICO PORTADA ALTA/49-50"
  },
  {
    "lat": 36.702545092993915,
    "lng": -4.461957104040086,
    "title": "AMIGOS DEL ABUELO VENTURA/51-52"
  },
  {
    "lat": 36.70288083234324,
    "lng": -4.462163323827246,
    "title": "AVOI/53-54"
  },
  {
    "lat": 36.703098834112545,
    "lng": -4.462281651319443,
    "title": "CENTRO CULTURAL RENFE/55-56"
  },
  {
    "lat": 36.70322463493213,
    "lng": -4.462337977710767,
    "title": "A.C.R. CICLISTA COSTA DE MÁLAGA/57"
  },
  {
    "lat": 36.703394519472816,
    "lng": -4.462447948284304,
    "title": "CASA DE ÁLORA-GIBRALFARO/58-59-60"
  },
  {
    "lat": 36.70382890610006,
    "lng": -4.462690688190864,
    "title": "PEÑA LOS ÁNGELES/61-62"
  },
  {
    "lat": 36.7040224438988,
    "lng": -4.4628006587644,
    "title": "LA EXQUISITA/63-64"
  },
  { "lat": 36.704162230370834, "lng": -4.462867570362459, "title": "ÁGAPE/65" },
  {
    "lat": 36.704391239577234,
    "lng": -4.463035352061581,
    "title": "EL SARAO/66-67-68"
  },
  {
    "lat": 36.70465896479709,
    "lng": -4.463204331218365,
    "title": "PEÑA EL SOMBRERO/69-70"
  },
  {
    "lat": 36.70490959995516,
    "lng": -4.463286094857431,
    "title": "BADAK/71-72"
  },
  {
    "lat": 36.70506149341888,
    "lng": -4.463360525032047,
    "title": "PUERTO 10/73"
  },
  {
    "lat": 36.70509764503675,
    "lng": -4.463437683410992,
    "title": "AA.VV. 13 DE NOVIEMBRE (LOS PRADOS)/74"
  },
  {
    "lat": 36.705315909027064,
    "lng": -4.46355838282097,
    "title": "LA MAMI (5º PINO)/75-76"
  },
  {
    "lat": 36.70552019497225,
    "lng": -4.463622755825453,
    "title": "El PATIO DE LICEO/77"
  },
  {
    "lat": 36.7056128160739,
    "lng": -4.463746456597386,
    "title": "EL EMBRUJO/78"
  },
  {
    "lat": 36.70587393090675,
    "lng": -4.463903046677515,
    "title": "TENTADERO/79-80"
  },
  {
    "lat": 36.701898235374586,
    "lng": -4.461284410565465,
    "title": "PEÑA LA ESTRELLA/85-86"
  },
  {
    "lat": 36.70220075363363,
    "lng": -4.461420645675038,
    "title": "PEÑA SANTA CRISTINA/87-88-89"
  },
  {
    "lat": 36.70239255480487,
    "lng": -4.461541854357054,
    "title": "PEÑA CORTIJO DE TORRE/90-91"
  },
  {
    "lat": 36.702521700657165,
    "lng": -4.46162478661317,
    "title": "PEÑA MALAGUISTA PERSONAS SORDAS/92"
  },
  {
    "lat": 36.70268409166846,
    "lng": -4.461739615890869,
    "title": "PEÑA EL BASTÓN/93/94"
  },
  {
    "lat": 36.70298107303786,
    "lng": -4.461919506134373,
    "title": "PEÑA EL PARRAL/95-96"
  },
  {
    "lat": 36.70317415092173,
    "lng": -4.461989679581855,
    "title": "BURGUER MI BARRIO/97"
  },
  {
    "lat": 36.70327132901092,
    "lng": -4.462058258178259,
    "title": "PEÑA TIRO DE PICHÓN/98-99"
  },
  {
    "lat": 36.70347975002469,
    "lng": -4.462168302902721,
    "title": "PEÑA LA PAZ/100-101-102"
  },
  {
    "lat": 36.703832400014434,
    "lng": -4.462419621326345,
    "title": "CLANDESTINO/103-104"
  },
  {
    "lat": 36.704071764927846,
    "lng": -4.462589343567235,
    "title": "CASA DE MELILLA/105-106"
  },
  {
    "lat": 36.7043075461241,
    "lng": -4.4627000976532205,
    "title": "MALA MÍA/107-108"
  },
  {
    "lat": 36.704493716600865,
    "lng": -4.462798269058603,
    "title": "CASAAMIGOS BOTANIC/109-110"
  },
  {
    "lat": 36.70478140961311,
    "lng": -4.462948185043132,
    "title": "UGT-CASA DEL PUEBLO/111-112"
  },
  {
    "lat": 36.70500261282751,
    "lng": -4.463056634916515,
    "title": "TEATRO GALLERY/113-114"
  },
  {
    "lat": 36.705013133018845,
    "lng": -4.463116422558839,
    "title": "CARAMELO/115"
  },
  { "lat": 36.7051598840898, "lng": -4.463141162023709, "title": "PLAN B/116" },
  {
    "lat": 36.705395377128184,
    "lng": -4.4633624773948535,
    "title": "LOS CLAVELES (RINCÓN CUBANO)/117-118"
  },
  {
    "lat": 36.705627860107015,
    "lng": -4.463456942519961,
    "title": "LA FERIA DE CANDELA/119-120-121"
  },
  {
    "lat": 36.705983864573994,
    "lng": -4.463601782121243,
    "title": "LA HUELLA DE MALAFAMA/122-123-124"
  },
  {
    "lat": 36.706285592566445,
    "lng": -4.46375597721681,
    "title": "GOLD/125-126"
  },
  {
    "lat": 36.70208793929987,
    "lng": -4.460712653459329,
    "title": "PEÑA EL PARCHÍS/127-128"
  },
  {
    "lat": 36.702339544042296,
    "lng": -4.460860174960415,
    "title": "PEÑA LA SOLERA/129-130"
  },
  {
    "lat": 36.70252125806626,
    "lng": -4.460963440011176,
    "title": "SARAO TROPICAL/131"
  },
  {
    "lat": 36.70255136449029,
    "lng": -4.4609728277430625,
    "title": "VIP REMEMBER/132"
  },
  {
    "lat": 36.70267716620595,
    "lng": -4.46106536395738,
    "title": "DUBAI/133-134"
  },
  { "lat": 36.70276856048563, "lng": -4.461114984825928, "title": "KOLOA/135" },
  {
    "lat": 36.7029319946913,
    "lng": -4.461200815517468,
    "title": "MARÍA DIABLA/136"
  },
  {
    "lat": 36.703146291653205,
    "lng": -4.461304157540526,
    "title": "MARITRINI BIANCO/137-138"
  },
  {
    "lat": 36.70328619986606,
    "lng": -4.461384660761136,
    "title": "EL ANDÉN/139"
  },
  {
    "lat": 36.70339574249634,
    "lng": -4.461475818923608,
    "title": "EL PATIO DE ANTOJO/140"
  },
  {
    "lat": 36.70358713095643,
    "lng": -4.461588471706255,
    "title": "ARTE/141-142"
  },
  {
    "lat": 36.70378706466731,
    "lng": -4.461681695668929,
    "title": "EL CALLEJÓN DE SEÑORÍO/143-144"
  },
  {
    "lat": 36.70412391393394,
    "lng": -4.461908179293234,
    "title": "GOLTAN CON ACENTO-TOUCHÉ/145-146"
  },
  {
    "lat": 36.70430777414858,
    "lng": -4.462012785448549,
    "title": "LA CONGA/147"
  },
  {
    "lat": 36.70442920745226,
    "lng": -4.4620381953673025,
    "title": "REY DE COPAS/148"
  },
  {
    "lat": 36.70448625791282,
    "lng": -4.462112027185643,
    "title": "JALEO/149-150"
  },
  {
    "lat": 36.70461528206259,
    "lng": -4.462173717995188,
    "title": "VIDA MÍA/151"
  },
  {
    "lat": 36.704731114300905,
    "lng": -4.462209175586649,
    "title": "LA RUINA/152"
  },
  {
    "lat": 36.704912680110716,
    "lng": -4.46226340051879,
    "title": "VELVET/153"
  },
  {
    "lat": 36.70515825633914,
    "lng": -4.462494241960641,
    "title": "SINDICATO DE ESTUDIANTES-LIBRES Y COMBATIVAS/154-155"
  },
  {
    "lat": 36.70530233203248,
    "lng": -4.462557273874741,
    "title": "EL MILITANTE-IZQUIERDA REVOLUCIONARIA/156"
  },
  {
    "lat": 36.70538942243257,
    "lng": -4.4626136002660655,
    "title": "LA PIJA/157"
  },
  {
    "lat": 36.70546361047333,
    "lng": -4.462691384330274,
    "title": "LA RUMBA/158"
  },
  { "lat": 36.7055281217549, "lng": -4.462718206421381, "title": "COLEGA/159" },
  {
    "lat": 36.705617362271774,
    "lng": -4.462763803976261,
    "title": "LUNARES/160"
  },
  {
    "lat": 36.70585000796829,
    "lng": -4.462881720616713,
    "title": "EL PALMEO/161-162"
  },
  {
    "lat": 36.70607257054184,
    "lng": -4.463015831072244,
    "title": "LA DESCARÁ/163"
  },
  {
    "lat": 36.70609776926862,
    "lng": -4.4630234970985185,
    "title": "ELIXIR/164"
  },
  {
    "lat": 36.706158584890325,
    "lng": -4.463061428627126,
    "title": "SALA PREMIEER/165"
  },
  {
    "lat": 36.70620911827516,
    "lng": -4.463115072809339,
    "title": "REINAS/166"
  },
  { "lat": 36.706332839955444, "lng": -4.463071803896306, "title": "MANÁ/167" },
  {
    "lat": 36.70646070952644,
    "lng": -4.463227725591987,
    "title": "MONKEY/168"
  },
  {
    "lat": 36.70243339192874,
    "lng": -4.46286677711333,
    "title": "LA CARRETA/169-170-171"
  },
  {
    "lat": 36.70286389291941,
    "lng": -4.463069061510696,
    "title": "LA SAL Y EL SON/172-173-174"
  },
  {
    "lat": 36.70295596854881,
    "lng": -4.462969252640704,
    "title": "INFORMACIÓN/175"
  },
  {
    "lat": 36.70311297119997,
    "lng": -4.463280804458847,
    "title": "MUNICIPAL DEL FLAMENCO Y LA COPLA/176-177-178-179"
  },
  {
    "lat": 36.703365952117906,
    "lng": -4.463355126208518,
    "title": "MUNICIPAL DEL MAYOR (EL RENGE)/180-181-182-183-184-185-186"
  },
  {
    "lat": 36.703898111359514,
    "lng": -4.463705043531029,
    "title": "EL ZAGUÁN DE PEPE HIGO/187"
  },
  {
    "lat": 36.70397405912844,
    "lng": -4.4639644214340315,
    "title": "LA PAVA/188"
  },
  {
    "lat": 36.70417296959616,
    "lng": -4.4638223274523865,
    "title": "LA REBOTICA DE D. HILARIÓN/189-190"
  },
  {
    "lat": 36.704213029133626,
    "lng": -4.463768754287378,
    "title": "LA ESPIGA/191"
  },
  {
    "lat": 36.704060240561134,
    "lng": -4.4640845205806805,
    "title": "EL PÉNDULO/192"
  },
  {
    "lat": 36.70418977908995,
    "lng": -4.464227920584463,
    "title": "MUNICIPAL - SAN MIGUEL/193-194-195"
  },
  {
    "lat": 36.7043096142749,
    "lng": -4.464346252519278,
    "title": "EL GAZPACHUELO/196"
  },
  {
    "lat": 36.7044941653739,
    "lng": -4.464123346823406,
    "title": "LA JARANA/197"
  },
  {
    "lat": 36.70455138436117,
    "lng": -4.464139522218394,
    "title": "A.R.C. EL PORTÓN/198-199-200"
  },
  {
    "lat": 36.7046806322106,
    "lng": -4.464186937424798,
    "title": "SIEMPRE ASÍ/201-202"
  },
  {
    "lat": 36.70476882473384,
    "lng": -4.464241939064069,
    "title": "MAMA JUANA LOMBOK/203"
  },
  {
    "lat": 36.70499386727442,
    "lng": -4.4642912508684995,
    "title": "LA BUGANVILLA/204"
  },
  {
    "lat": 36.705145639438655,
    "lng": -4.464435162498763,
    "title": "LOS VERDIALES/205-206-207-208"
  },
  {
    "lat": 36.70538008738478,
    "lng": -4.464575742101163,
    "title": "MARUJA LIMÓN/209"
  },
  {
    "lat": 36.70546371746714,
    "lng": -4.4646307437404325,
    "title": "LOS COLORAOS/210"
  },
  {
    "lat": 36.70560584123441,
    "lng": -4.464689933295453,
    "title": "LA NORIA/211"
  },
  {
    "lat": 36.70182551450698,
    "lng": -4.462565788211993,
    "title": "PURA ESENCIA/212-213"
  },
  {
    "lat": 36.70660934237448,
    "lng": -4.464140598255172,
    "title": "PORTADA 2"
  },
  {
    "lat": 36.7020589553713,
    "lng": -4.459665768417117,
    "title": "PORTADA 1"
  },
  {
    "lat": 36.70185714248503,
    "lng": -4.460820161769223,
    "title": "BAÑOS WC 1"
  },
  {
    "lat": 36.70574941763382,
    "lng": -4.464769211424459,
    "title": "BAÑOS WC 2"
  },
  {
    "lat": 36.706489140997924,
    "lng": -4.462623444145515,
    "title": "ZONA JUVENTUD"
  },
  {
    "lat": 36.70227182313761,
    "lng": -4.460606492390465,
    "title": "CAJERO"
  },
  {
    "lat": 36.70243095507729,
    "lng": -4.460606492390465,
    "title": "INFANTIL"
  },
  {
    "lat": 36.70259370331118,
    "lng": -4.460480186629003,
    "title": "POLICIA/BOMBEROS/SANITARIOS/OBJETOS PERDIDOS"
  },
  {
    "lat": 36.7009206149272,
    "lng": -4.459557603011988,
    "title": "BUS / TAXI"
  }
]
